simple_tsdb/__init__.py
simple_tsdb/client.py
simple_tsdb/push_queue.py
simple_tsdb-0.9.9.dist-info/METADATA
simple_tsdb-0.9.9.dist-info/WHEEL
simple_tsdb-0.9.9.dist-info/top_level.txt
simple_tsdb-0.9.9.dist-info/RECORD
